vowpal_wabbit_next/__init__.py
vowpal_wabbit_next/_core.cp37-win_amd64.pyd
vowpal_wabbit_next/_core.pyi
vowpal_wabbit_next/cache_format.py
vowpal_wabbit_next/cli_driver.py
vowpal_wabbit_next/delta.py
vowpal_wabbit_next/dsjson_format.py
vowpal_wabbit_next/example.py
vowpal_wabbit_next/json_format.py
vowpal_wabbit_next/labels.py
vowpal_wabbit_next/prediction_type.py
vowpal_wabbit_next/py.typed
vowpal_wabbit_next/text_format.py
vowpal_wabbit_next/workspace.py
vowpal_wabbit_next-0.7.0.dist-info/LICENSE
vowpal_wabbit_next-0.7.0.dist-info/METADATA
vowpal_wabbit_next-0.7.0.dist-info/WHEEL
vowpal_wabbit_next-0.7.0.dist-info/top_level.txt
vowpal_wabbit_next-0.7.0.dist-info/RECORD
