Metadata-Version: 2.1
Name: vowpal-wabbit-next
Version: 0.7.0
Summary: Experimental python bindings for VowpalWabbit
Author: VowpalWabbit
License: BSD-3-Clause
Requires-Python: >=3.7
License-File: LICENSE
Requires-Dist: numpy
Requires-Dist: typing-extensions ; python_version == "3.7"
